{"isFileChange": "True", "isIssuesChange": "False", "data": [{"fileNow": {"line": 0, "issues": []}, "fileBefore": {"line": 0, "issues": []}}, {"fileNow": {"line": "1", "commitId": "easyexcel_349", "commitHash": "3a74fabae5454b15813732cfbc6e33be0c9cf0b2", "commiter": "clevertension <zdan0803@gmail.com>", "date": "2019-06-28 17:52:02", "context": "package com.alibaba.excel.analysis.v03;", "issues": []}, "fileBefore": {"line": "", "commitId": "", "commitHash": "", "commiter": "", "date": "", "context": "", "issues": []}}, {"fileNow": {"line": "2", "commitId": "easyexcel_349", "commitHash": "3a74fabae5454b15813732cfbc6e33be0c9cf0b2", "commiter": "clevertension <zdan0803@gmail.com>", "date": "2019-06-28 17:52:02", "context": "", "issues": []}, "fileBefore": {"line": "", "commitId": "", "commitHash": "", "commiter": "", "date": "", "context": "", "issues": []}}, {"fileNow": {"line": "3", "commitId": "easyexcel_349", "commitHash": "3a74fabae5454b15813732cfbc6e33be0c9cf0b2", "commiter": "clevertension <zdan0803@gmail.com>", "date": "2019-06-28 17:52:02", "context": "public abstract class AbstractXlsRecordHandler implements XlsRecordHandler {", "issues": []}, "fileBefore": {"line": "", "commitId": "", "commitHash": "", "commiter": "", "date": "", "context": "", "issues": []}}, {"fileNow": {"line": "4", "commitId": "easyexcel_349", "commitHash": "3a74fabae5454b15813732cfbc6e33be0c9cf0b2", "commiter": "clevertension <zdan0803@gmail.com>", "date": "2019-06-28 17:52:02", "context": "    protected int row = -1;", "issues": []}, "fileBefore": {"line": "", "commitId": "", "commitHash": "", "commiter": "", "date": "", "context": "", "issues": []}}, {"fileNow": {"line": "5", "commitId": "easyexcel_349", "commitHash": "3a74fabae5454b15813732cfbc6e33be0c9cf0b2", "commiter": "clevertension <zdan0803@gmail.com>", "date": "2019-06-28 17:52:02", "context": "    protected int column = -1;", "issues": []}, "fileBefore": {"line": "", "commitId": "", "commitHash": "", "commiter": "", "date": "", "context": "", "issues": []}}, {"fileNow": {"line": "6", "commitId": "easyexcel_349", "commitHash": "3a74fabae5454b15813732cfbc6e33be0c9cf0b2", "commiter": "clevertension <zdan0803@gmail.com>", "date": "2019-06-28 17:52:02", "context": "    protected String value = null;", "issues": []}, "fileBefore": {"line": "", "commitId": "", "commitHash": "", "commiter": "", "date": "", "context": "", "issues": []}}, {"fileNow": {"line": "7", "commitId": "easyexcel_349", "commitHash": "3a74fabae5454b15813732cfbc6e33be0c9cf0b2", "commiter": "clevertension <zdan0803@gmail.com>", "date": "2019-06-28 17:52:02", "context": "", "issues": []}, "fileBefore": {"line": "", "commitId": "", "commitHash": "", "commiter": "", "date": "", "context": "", "issues": []}}, {"fileNow": {"line": "8", "commitId": "easyexcel_349", "commitHash": "3a74fabae5454b15813732cfbc6e33be0c9cf0b2", "commiter": "clevertension <zdan0803@gmail.com>", "date": "2019-06-28 17:52:02", "context": "    @Override", "issues": []}, "fileBefore": {"line": "", "commitId": "", "commitHash": "", "commiter": "", "date": "", "context": "", "issues": []}}, {"fileNow": {"line": "9", "commitId": "easyexcel_349", "commitHash": "3a74fabae5454b15813732cfbc6e33be0c9cf0b2", "commiter": "clevertension <zdan0803@gmail.com>", "date": "2019-06-28 17:52:02", "context": "    public int getRow() {", "issues": []}, "fileBefore": {"line": "", "commitId": "", "commitHash": "", "commiter": "", "date": "", "context": "", "issues": []}}, {"fileNow": {"line": "10", "commitId": "easyexcel_349", "commitHash": "3a74fabae5454b15813732cfbc6e33be0c9cf0b2", "commiter": "clevertension <zdan0803@gmail.com>", "date": "2019-06-28 17:52:02", "context": "        return row;", "issues": []}, "fileBefore": {"line": "", "commitId": "", "commitHash": "", "commiter": "", "date": "", "context": "", "issues": []}}, {"fileNow": {"line": "11", "commitId": "easyexcel_349", "commitHash": "3a74fabae5454b15813732cfbc6e33be0c9cf0b2", "commiter": "clevertension <zdan0803@gmail.com>", "date": "2019-06-28 17:52:02", "context": "    }", "issues": []}, "fileBefore": {"line": "", "commitId": "", "commitHash": "", "commiter": "", "date": "", "context": "", "issues": []}}, {"fileNow": {"line": "12", "commitId": "easyexcel_349", "commitHash": "3a74fabae5454b15813732cfbc6e33be0c9cf0b2", "commiter": "clevertension <zdan0803@gmail.com>", "date": "2019-06-28 17:52:02", "context": "", "issues": []}, "fileBefore": {"line": "", "commitId": "", "commitHash": "", "commiter": "", "date": "", "context": "", "issues": []}}, {"fileNow": {"line": "13", "commitId": "easyexcel_349", "commitHash": "3a74fabae5454b15813732cfbc6e33be0c9cf0b2", "commiter": "clevertension <zdan0803@gmail.com>", "date": "2019-06-28 17:52:02", "context": "    @Override", "issues": []}, "fileBefore": {"line": "", "commitId": "", "commitHash": "", "commiter": "", "date": "", "context": "", "issues": []}}, {"fileNow": {"line": "14", "commitId": "easyexcel_349", "commitHash": "3a74fabae5454b15813732cfbc6e33be0c9cf0b2", "commiter": "clevertension <zdan0803@gmail.com>", "date": "2019-06-28 17:52:02", "context": "    public int getColumn() {", "issues": []}, "fileBefore": {"line": "", "commitId": "", "commitHash": "", "commiter": "", "date": "", "context": "", "issues": []}}, {"fileNow": {"line": "15", "commitId": "easyexcel_349", "commitHash": "3a74fabae5454b15813732cfbc6e33be0c9cf0b2", "commiter": "clevertension <zdan0803@gmail.com>", "date": "2019-06-28 17:52:02", "context": "        return column;", "issues": []}, "fileBefore": {"line": "", "commitId": "", "commitHash": "", "commiter": "", "date": "", "context": "", "issues": []}}, {"fileNow": {"line": "16", "commitId": "easyexcel_349", "commitHash": "3a74fabae5454b15813732cfbc6e33be0c9cf0b2", "commiter": "clevertension <zdan0803@gmail.com>", "date": "2019-06-28 17:52:02", "context": "    }", "issues": []}, "fileBefore": {"line": "", "commitId": "", "commitHash": "", "commiter": "", "date": "", "context": "", "issues": []}}, {"fileNow": {"line": "17", "commitId": "easyexcel_349", "commitHash": "3a74fabae5454b15813732cfbc6e33be0c9cf0b2", "commiter": "clevertension <zdan0803@gmail.com>", "date": "2019-06-28 17:52:02", "context": "", "issues": []}, "fileBefore": {"line": "", "commitId": "", "commitHash": "", "commiter": "", "date": "", "context": "", "issues": []}}, {"fileNow": {"line": "18", "commitId": "easyexcel_349", "commitHash": "3a74fabae5454b15813732cfbc6e33be0c9cf0b2", "commiter": "clevertension <zdan0803@gmail.com>", "date": "2019-06-28 17:52:02", "context": "    @Override", "issues": []}, "fileBefore": {"line": "", "commitId": "", "commitHash": "", "commiter": "", "date": "", "context": "", "issues": []}}, {"fileNow": {"line": "19", "commitId": "easyexcel_349", "commitHash": "3a74fabae5454b15813732cfbc6e33be0c9cf0b2", "commiter": "clevertension <zdan0803@gmail.com>", "date": "2019-06-28 17:52:02", "context": "    public String getValue() {", "issues": []}, "fileBefore": {"line": "", "commitId": "", "commitHash": "", "commiter": "", "date": "", "context": "", "issues": []}}, {"fileNow": {"line": "20", "commitId": "easyexcel_349", "commitHash": "3a74fabae5454b15813732cfbc6e33be0c9cf0b2", "commiter": "clevertension <zdan0803@gmail.com>", "date": "2019-06-28 17:52:02", "context": "        return value;", "issues": []}, "fileBefore": {"line": "", "commitId": "", "commitHash": "", "commiter": "", "date": "", "context": "", "issues": []}}, {"fileNow": {"line": "21", "commitId": "easyexcel_349", "commitHash": "3a74fabae5454b15813732cfbc6e33be0c9cf0b2", "commiter": "clevertension <zdan0803@gmail.com>", "date": "2019-06-28 17:52:02", "context": "    }", "issues": []}, "fileBefore": {"line": "", "commitId": "", "commitHash": "", "commiter": "", "date": "", "context": "", "issues": []}}, {"fileNow": {"line": "22", "commitId": "easyexcel_349", "commitHash": "3a74fabae5454b15813732cfbc6e33be0c9cf0b2", "commiter": "clevertension <zdan0803@gmail.com>", "date": "2019-06-28 17:52:02", "context": "", "issues": []}, "fileBefore": {"line": "", "commitId": "", "commitHash": "", "commiter": "", "date": "", "context": "", "issues": []}}, {"fileNow": {"line": "23", "commitId": "easyexcel_349", "commitHash": "3a74fabae5454b15813732cfbc6e33be0c9cf0b2", "commiter": "clevertension <zdan0803@gmail.com>", "date": "2019-06-28 17:52:02", "context": "    @Override", "issues": []}, "fileBefore": {"line": "", "commitId": "", "commitHash": "", "commiter": "", "date": "", "context": "", "issues": []}}, {"fileNow": {"line": "24", "commitId": "easyexcel_349", "commitHash": "3a74fabae5454b15813732cfbc6e33be0c9cf0b2", "commiter": "clevertension <zdan0803@gmail.com>", "date": "2019-06-28 17:52:02", "context": "    public int compareTo(XlsRecordHandler o) {", "issues": []}, "fileBefore": {"line": "", "commitId": "", "commitHash": "", "commiter": "", "date": "", "context": "", "issues": []}}, {"fileNow": {"line": "25", "commitId": "easyexcel_349", "commitHash": "3a74fabae5454b15813732cfbc6e33be0c9cf0b2", "commiter": "clevertension <zdan0803@gmail.com>", "date": "2019-06-28 17:52:02", "context": "        return this.getOrder() - o.getOrder();", "issues": []}, "fileBefore": {"line": "", "commitId": "", "commitHash": "", "commiter": "", "date": "", "context": "", "issues": []}}, {"fileNow": {"line": "26", "commitId": "easyexcel_349", "commitHash": "3a74fabae5454b15813732cfbc6e33be0c9cf0b2", "commiter": "clevertension <zdan0803@gmail.com>", "date": "2019-06-28 17:52:02", "context": "    }", "issues": []}, "fileBefore": {"line": "", "commitId": "", "commitHash": "", "commiter": "", "date": "", "context": "", "issues": []}}, {"fileNow": {"line": "27", "commitId": "easyexcel_349", "commitHash": "3a74fabae5454b15813732cfbc6e33be0c9cf0b2", "commiter": "clevertension <zdan0803@gmail.com>", "date": "2019-06-28 17:52:02", "context": "}", "issues": []}, "fileBefore": {"line": "", "commitId": "", "commitHash": "", "commiter": "", "date": "", "context": "", "issues": []}}]}