{"isFileChange": "True", "isIssuesChange": "False", "data": [{"fileNow": {"line": 0, "issues": []}, "fileBefore": {"line": 0, "issues": []}}, {"fileNow": {"line": "1", "commitId": "easyexcel_312", "commitHash": "a9b2f480dbd5c7498f8c7be61182ba80d7a2fd98", "commiter": "zhuangjiaju <jiaju.zhuang@ideacome.com>", "date": "2019-08-01 21:05:29", "context": "package com.alibaba.excel.enums;", "issues": []}, "fileBefore": {"line": "1", "commitId": "easyexcel_312", "commitHash": "a9b2f480dbd5c7498f8c7be61182ba80d7a2fd98", "commiter": "zhuangjiaju <jiaju.zhuang@ideacome.com>", "date": "2019-08-01 21:05:29", "context": "package com.alibaba.excel.enums;", "issues": []}}, {"fileNow": {"line": "2", "commitId": "easyexcel_312", "commitHash": "a9b2f480dbd5c7498f8c7be61182ba80d7a2fd98", "commiter": "zhuangjiaju <jiaju.zhuang@ideacome.com>", "date": "2019-08-01 21:05:29", "context": "", "issues": []}, "fileBefore": {"line": "2", "commitId": "easyexcel_312", "commitHash": "a9b2f480dbd5c7498f8c7be61182ba80d7a2fd98", "commiter": "zhuangjiaju <jiaju.zhuang@ideacome.com>", "date": "2019-08-01 21:05:29", "context": "", "issues": []}}, {"fileNow": {"line": "3", "commitId": "easyexcel_312", "commitHash": "a9b2f480dbd5c7498f8c7be61182ba80d7a2fd98", "commiter": "zhuangjiaju <jiaju.zhuang@ideacome.com>", "date": "2019-08-01 21:05:29", "context": "/**", "issues": []}, "fileBefore": {"line": "3", "commitId": "easyexcel_312", "commitHash": "a9b2f480dbd5c7498f8c7be61182ba80d7a2fd98", "commiter": "zhuangjiaju <jiaju.zhuang@ideacome.com>", "date": "2019-08-01 21:05:29", "context": "/**", "issues": []}}, {"fileNow": {"line": "4", "commitId": "easyexcel_312", "commitHash": "a9b2f480dbd5c7498f8c7be61182ba80d7a2fd98", "commiter": "zhuangjiaju <jiaju.zhuang@ideacome.com>", "date": "2019-08-01 21:05:29", "context": " * The types of write last row", "issues": []}, "fileBefore": {"line": "4", "commitId": "easyexcel_312", "commitHash": "a9b2f480dbd5c7498f8c7be61182ba80d7a2fd98", "commiter": "zhuangjiaju <jiaju.zhuang@ideacome.com>", "date": "2019-08-01 21:05:29", "context": " * The types of write last row", "issues": []}}, {"fileNow": {"line": "5", "commitId": "easyexcel_312", "commitHash": "a9b2f480dbd5c7498f8c7be61182ba80d7a2fd98", "commiter": "zhuangjiaju <jiaju.zhuang@ideacome.com>", "date": "2019-08-01 21:05:29", "context": " *", "issues": []}, "fileBefore": {"line": "5", "commitId": "easyexcel_312", "commitHash": "a9b2f480dbd5c7498f8c7be61182ba80d7a2fd98", "commiter": "zhuangjiaju <jiaju.zhuang@ideacome.com>", "date": "2019-08-01 21:05:29", "context": " *", "issues": []}}, {"fileNow": {"line": "6", "commitId": "easyexcel_305", "commitHash": "4318be5724fc661688ca60396b0dc709514db315", "commiter": "zhuangjiaju <jiaju.zhuang@ideacome.com>", "date": "2019-08-06 10:13:37", "context": " * @author Jiaju Zhuang", "issues": []}, "fileBefore": {"line": "", "commitId": "", "commitHash": "", "commiter": "", "date": "", "context": "", "issues": []}}, {"fileNow": {"line": "", "commitId": "", "commitHash": "", "commiter": "", "date": "", "context": "", "issues": []}, "fileBefore": {"line": "6", "commitId": "easyexcel_312", "commitHash": "a9b2f480dbd5c7498f8c7be61182ba80d7a2fd98", "commiter": "zhuangjiaju <jiaju.zhuang@ideacome.com>", "date": "2019-08-01 21:05:29", "context": " * @author zhuangjiaju", "issues": []}}, {"fileNow": {"line": "7", "commitId": "easyexcel_312", "commitHash": "a9b2f480dbd5c7498f8c7be61182ba80d7a2fd98", "commiter": "zhuangjiaju <jiaju.zhuang@ideacome.com>", "date": "2019-08-01 21:05:29", "context": " **/", "issues": []}, "fileBefore": {"line": "7", "commitId": "easyexcel_312", "commitHash": "a9b2f480dbd5c7498f8c7be61182ba80d7a2fd98", "commiter": "zhuangjiaju <jiaju.zhuang@ideacome.com>", "date": "2019-08-01 21:05:29", "context": " **/", "issues": []}}, {"fileNow": {"line": "8", "commitId": "easyexcel_312", "commitHash": "a9b2f480dbd5c7498f8c7be61182ba80d7a2fd98", "commiter": "zhuangjiaju <jiaju.zhuang@ideacome.com>", "date": "2019-08-01 21:05:29", "context": "public enum WriteLastRowType {", "issues": []}, "fileBefore": {"line": "8", "commitId": "easyexcel_312", "commitHash": "a9b2f480dbd5c7498f8c7be61182ba80d7a2fd98", "commiter": "zhuangjiaju <jiaju.zhuang@ideacome.com>", "date": "2019-08-01 21:05:29", "context": "public enum WriteLastRowType {", "issues": []}}, {"fileNow": {"line": "9", "commitId": "easyexcel_312", "commitHash": "a9b2f480dbd5c7498f8c7be61182ba80d7a2fd98", "commiter": "zhuangjiaju <jiaju.zhuang@ideacome.com>", "date": "2019-08-01 21:05:29", "context": "    /**", "issues": []}, "fileBefore": {"line": "9", "commitId": "easyexcel_312", "commitHash": "a9b2f480dbd5c7498f8c7be61182ba80d7a2fd98", "commiter": "zhuangjiaju <jiaju.zhuang@ideacome.com>", "date": "2019-08-01 21:05:29", "context": "    /**", "issues": []}}, {"fileNow": {"line": "10", "commitId": "easyexcel_312", "commitHash": "a9b2f480dbd5c7498f8c7be61182ba80d7a2fd98", "commiter": "zhuangjiaju <jiaju.zhuang@ideacome.com>", "date": "2019-08-01 21:05:29", "context": "     * Tables are created without templates ,And any data has been written;", "issues": []}, "fileBefore": {"line": "10", "commitId": "easyexcel_312", "commitHash": "a9b2f480dbd5c7498f8c7be61182ba80d7a2fd98", "commiter": "zhuangjiaju <jiaju.zhuang@ideacome.com>", "date": "2019-08-01 21:05:29", "context": "     * Tables are created without templates ,And any data has been written;", "issues": []}}, {"fileNow": {"line": "11", "commitId": "easyexcel_312", "commitHash": "a9b2f480dbd5c7498f8c7be61182ba80d7a2fd98", "commiter": "zhuangjiaju <jiaju.zhuang@ideacome.com>", "date": "2019-08-01 21:05:29", "context": "     */", "issues": []}, "fileBefore": {"line": "11", "commitId": "easyexcel_312", "commitHash": "a9b2f480dbd5c7498f8c7be61182ba80d7a2fd98", "commiter": "zhuangjiaju <jiaju.zhuang@ideacome.com>", "date": "2019-08-01 21:05:29", "context": "     */", "issues": []}}, {"fileNow": {"line": "12", "commitId": "easyexcel_312", "commitHash": "a9b2f480dbd5c7498f8c7be61182ba80d7a2fd98", "commiter": "zhuangjiaju <jiaju.zhuang@ideacome.com>", "date": "2019-08-01 21:05:29", "context": "    EMPTY,", "issues": []}, "fileBefore": {"line": "12", "commitId": "easyexcel_312", "commitHash": "a9b2f480dbd5c7498f8c7be61182ba80d7a2fd98", "commiter": "zhuangjiaju <jiaju.zhuang@ideacome.com>", "date": "2019-08-01 21:05:29", "context": "    EMPTY,", "issues": []}}, {"fileNow": {"line": "13", "commitId": "easyexcel_312", "commitHash": "a9b2f480dbd5c7498f8c7be61182ba80d7a2fd98", "commiter": "zhuangjiaju <jiaju.zhuang@ideacome.com>", "date": "2019-08-01 21:05:29", "context": "    /**", "issues": []}, "fileBefore": {"line": "13", "commitId": "easyexcel_312", "commitHash": "a9b2f480dbd5c7498f8c7be61182ba80d7a2fd98", "commiter": "zhuangjiaju <jiaju.zhuang@ideacome.com>", "date": "2019-08-01 21:05:29", "context": "    /**", "issues": []}}, {"fileNow": {"line": "14", "commitId": "easyexcel_312", "commitHash": "a9b2f480dbd5c7498f8c7be61182ba80d7a2fd98", "commiter": "zhuangjiaju <jiaju.zhuang@ideacome.com>", "date": "2019-08-01 21:05:29", "context": "     * It's supposed to have data in it.Tables are created with templates ,or any data has been written;", "issues": []}, "fileBefore": {"line": "14", "commitId": "easyexcel_312", "commitHash": "a9b2f480dbd5c7498f8c7be61182ba80d7a2fd98", "commiter": "zhuangjiaju <jiaju.zhuang@ideacome.com>", "date": "2019-08-01 21:05:29", "context": "     * It's supposed to have data in it.Tables are created with templates ,or any data has been written;", "issues": []}}, {"fileNow": {"line": "15", "commitId": "easyexcel_312", "commitHash": "a9b2f480dbd5c7498f8c7be61182ba80d7a2fd98", "commiter": "zhuangjiaju <jiaju.zhuang@ideacome.com>", "date": "2019-08-01 21:05:29", "context": "     */", "issues": []}, "fileBefore": {"line": "15", "commitId": "easyexcel_312", "commitHash": "a9b2f480dbd5c7498f8c7be61182ba80d7a2fd98", "commiter": "zhuangjiaju <jiaju.zhuang@ideacome.com>", "date": "2019-08-01 21:05:29", "context": "     */", "issues": []}}, {"fileNow": {"line": "16", "commitId": "easyexcel_312", "commitHash": "a9b2f480dbd5c7498f8c7be61182ba80d7a2fd98", "commiter": "zhuangjiaju <jiaju.zhuang@ideacome.com>", "date": "2019-08-01 21:05:29", "context": "    HAVE_DATA,;", "issues": []}, "fileBefore": {"line": "16", "commitId": "easyexcel_312", "commitHash": "a9b2f480dbd5c7498f8c7be61182ba80d7a2fd98", "commiter": "zhuangjiaju <jiaju.zhuang@ideacome.com>", "date": "2019-08-01 21:05:29", "context": "    HAVE_DATA,;", "issues": []}}, {"fileNow": {"line": "17", "commitId": "easyexcel_312", "commitHash": "a9b2f480dbd5c7498f8c7be61182ba80d7a2fd98", "commiter": "zhuangjiaju <jiaju.zhuang@ideacome.com>", "date": "2019-08-01 21:05:29", "context": "}", "issues": []}, "fileBefore": {"line": "17", "commitId": "easyexcel_312", "commitHash": "a9b2f480dbd5c7498f8c7be61182ba80d7a2fd98", "commiter": "zhuangjiaju <jiaju.zhuang@ideacome.com>", "date": "2019-08-01 21:05:29", "context": "}", "issues": []}}]}