{"isFileChange": "False", "isIssuesChange": "False", "data": [{"line": 0, "issues": []}, {"line": 1, "commitId": "easyexcel_107", "commitHash": "e63190976af92983c9e3e1de6c065628bc26b3b7", "commiter": "Jiaju Zhuang <zhuangjiaju@qq.com>", "date": "2020-03-15 04:06:04", "context": "package com.alibaba.excel.analysis.v07.handlers;", "issues": []}, {"line": 2, "commitId": "easyexcel_107", "commitHash": "e63190976af92983c9e3e1de6c065628bc26b3b7", "commiter": "Jiaju Zhuang <zhuangjiaju@qq.com>", "date": "2020-03-15 04:06:04", "context": "", "issues": []}, {"line": 3, "commitId": "easyexcel_107", "commitHash": "e63190976af92983c9e3e1de6c065628bc26b3b7", "commiter": "Jiaju Zhuang <zhuangjiaju@qq.com>", "date": "2020-03-15 04:06:04", "context": "import java.util.LinkedHashMap;", "issues": []}, {"line": 4, "commitId": "easyexcel_107", "commitHash": "e63190976af92983c9e3e1de6c065628bc26b3b7", "commiter": "Jiaju Zhuang <zhuangjiaju@qq.com>", "date": "2020-03-15 04:06:04", "context": "", "issues": []}, {"line": 5, "commitId": "easyexcel_107", "commitHash": "e63190976af92983c9e3e1de6c065628bc26b3b7", "commiter": "Jiaju Zhuang <zhuangjiaju@qq.com>", "date": "2020-03-15 04:06:04", "context": "import org.xml.sax.Attributes;", "issues": []}, {"line": 6, "commitId": "easyexcel_107", "commitHash": "e63190976af92983c9e3e1de6c065628bc26b3b7", "commiter": "Jiaju Zhuang <zhuangjiaju@qq.com>", "date": "2020-03-15 04:06:04", "context": "", "issues": []}, {"line": 7, "commitId": "easyexcel_107", "commitHash": "e63190976af92983c9e3e1de6c065628bc26b3b7", "commiter": "Jiaju Zhuang <zhuangjiaju@qq.com>", "date": "2020-03-15 04:06:04", "context": "import com.alibaba.excel.constant.ExcelXmlConstants;", "issues": []}, {"line": 8, "commitId": "easyexcel_107", "commitHash": "e63190976af92983c9e3e1de6c065628bc26b3b7", "commiter": "Jiaju Zhuang <zhuangjiaju@qq.com>", "date": "2020-03-15 04:06:04", "context": "import com.alibaba.excel.context.xlsx.XlsxReadContext;", "issues": []}, {"line": 9, "commitId": "easyexcel_107", "commitHash": "e63190976af92983c9e3e1de6c065628bc26b3b7", "commiter": "Jiaju Zhuang <zhuangjiaju@qq.com>", "date": "2020-03-15 04:06:04", "context": "import com.alibaba.excel.enums.RowTypeEnum;", "issues": []}, {"line": 10, "commitId": "easyexcel_107", "commitHash": "e63190976af92983c9e3e1de6c065628bc26b3b7", "commiter": "Jiaju Zhuang <zhuangjiaju@qq.com>", "date": "2020-03-15 04:06:04", "context": "import com.alibaba.excel.metadata.Cell;", "issues": []}, {"line": 11, "commitId": "easyexcel_107", "commitHash": "e63190976af92983c9e3e1de6c065628bc26b3b7", "commiter": "Jiaju Zhuang <zhuangjiaju@qq.com>", "date": "2020-03-15 04:06:04", "context": "import com.alibaba.excel.read.metadata.holder.ReadRowHolder;", "issues": []}, {"line": 13, "commitId": "easyexcel_107", "commitHash": "e63190976af92983c9e3e1de6c065628bc26b3b7", "commiter": "Jiaju Zhuang <zhuangjiaju@qq.com>", "date": "2020-03-15 04:06:04", "context": "import com.alibaba.excel.util.PositionUtils;", "issues": []}, {"line": 14, "commitId": "easyexcel_107", "commitHash": "e63190976af92983c9e3e1de6c065628bc26b3b7", "commiter": "Jiaju Zhuang <zhuangjiaju@qq.com>", "date": "2020-03-15 04:06:04", "context": "", "issues": []}, {"line": 15, "commitId": "easyexcel_107", "commitHash": "e63190976af92983c9e3e1de6c065628bc26b3b7", "commiter": "Jiaju Zhuang <zhuangjiaju@qq.com>", "date": "2020-03-15 04:06:04", "context": "/**", "issues": []}, {"line": 16, "commitId": "easyexcel_107", "commitHash": "e63190976af92983c9e3e1de6c065628bc26b3b7", "commiter": "Jiaju Zhuang <zhuangjiaju@qq.com>", "date": "2020-03-15 04:06:04", "context": " * Cell Handler", "issues": []}, {"line": 17, "commitId": "easyexcel_107", "commitHash": "e63190976af92983c9e3e1de6c065628bc26b3b7", "commiter": "Jiaju Zhuang <zhuangjiaju@qq.com>", "date": "2020-03-15 04:06:04", "context": " *", "issues": []}, {"line": 18, "commitId": "easyexcel_107", "commitHash": "e63190976af92983c9e3e1de6c065628bc26b3b7", "commiter": "Jiaju Zhuang <zhuangjiaju@qq.com>", "date": "2020-03-15 04:06:04", "context": " * @author jipengfei", "issues": []}, {"line": 19, "commitId": "easyexcel_107", "commitHash": "e63190976af92983c9e3e1de6c065628bc26b3b7", "commiter": "Jiaju Zhuang <zhuangjiaju@qq.com>", "date": "2020-03-15 04:06:04", "context": " */", "issues": []}, {"line": 20, "commitId": "easyexcel_107", "commitHash": "e63190976af92983c9e3e1de6c065628bc26b3b7", "commiter": "Jiaju Zhuang <zhuangjiaju@qq.com>", "date": "2020-03-15 04:06:04", "context": "public class RowTagHandler extends AbstractXlsxTagHandler {", "issues": []}, {"line": 21, "commitId": "easyexcel_107", "commitHash": "e63190976af92983c9e3e1de6c065628bc26b3b7", "commiter": "Jiaju Zhuang <zhuangjiaju@qq.com>", "date": "2020-03-15 04:06:04", "context": "", "issues": []}, {"line": 22, "commitId": "easyexcel_107", "commitHash": "e63190976af92983c9e3e1de6c065628bc26b3b7", "commiter": "Jiaju Zhuang <zhuangjiaju@qq.com>", "date": "2020-03-15 04:06:04", "context": "    @Override", "issues": []}, {"line": 23, "commitId": "easyexcel_107", "commitHash": "e63190976af92983c9e3e1de6c065628bc26b3b7", "commiter": "Jiaju Zhuang <zhuangjiaju@qq.com>", "date": "2020-03-15 04:06:04", "context": "    public void startElement(XlsxReadContext xlsxReadContext, String name, Attributes attributes) {", "issues": []}, {"line": 32, "commitId": "easyexcel_103", "commitHash": "f99c198df7601e6967f425008aacdb886c6be63d", "commiter": "Jiaju Zhuang <zhuangjiaju@qq.com>", "date": "2020-03-16 02:07:18", "context": "                xlsxReadContext.analysisEventProcessor().endRow(xlsxReadContext);", "issues": []}, {"line": 36, "commitId": "easyexcel_103", "commitHash": "f99c198df7601e6967f425008aacdb886c6be63d", "commiter": "Jiaju Zhuang <zhuangjiaju@qq.com>", "date": "2020-03-16 02:07:18", "context": "            }", "issues": []}, {"line": 37, "commitId": "easyexcel_103", "commitHash": "f99c198df7601e6967f425008aacdb886c6be63d", "commiter": "Jiaju Zhuang <zhuangjiaju@qq.com>", "date": "2020-03-16 02:07:18", "context": "        }", "issues": []}, {"line": 39, "commitId": "easyexcel_107", "commitHash": "e63190976af92983c9e3e1de6c065628bc26b3b7", "commiter": "Jiaju Zhuang <zhuangjiaju@qq.com>", "date": "2020-03-15 04:06:04", "context": "    }", "issues": []}, {"line": 40, "commitId": "easyexcel_107", "commitHash": "e63190976af92983c9e3e1de6c065628bc26b3b7", "commiter": "Jiaju Zhuang <zhuangjiaju@qq.com>", "date": "2020-03-15 04:06:04", "context": "", "issues": []}, {"line": 41, "commitId": "easyexcel_107", "commitHash": "e63190976af92983c9e3e1de6c065628bc26b3b7", "commiter": "Jiaju Zhuang <zhuangjiaju@qq.com>", "date": "2020-03-15 04:06:04", "context": "    @Override", "issues": []}, {"line": 42, "commitId": "easyexcel_107", "commitHash": "e63190976af92983c9e3e1de6c065628bc26b3b7", "commiter": "Jiaju Zhuang <zhuangjiaju@qq.com>", "date": "2020-03-15 04:06:04", "context": "    public void endElement(XlsxReadContext xlsxReadContext, String name) {", "issues": []}, {"line": 46, "commitId": "easyexcel_107", "commitHash": "e63190976af92983c9e3e1de6c065628bc26b3b7", "commiter": "Jiaju Zhuang <zhuangjiaju@qq.com>", "date": "2020-03-15 04:06:04", "context": "        xlsxReadContext.analysisEventProcessor().endRow(xlsxReadContext);", "issues": []}, {"line": 49, "commitId": "easyexcel_107", "commitHash": "e63190976af92983c9e3e1de6c065628bc26b3b7", "commiter": "Jiaju Zhuang <zhuangjiaju@qq.com>", "date": "2020-03-15 04:06:04", "context": "    }", "issues": []}, {"line": 50, "commitId": "easyexcel_107", "commitHash": "e63190976af92983c9e3e1de6c065628bc26b3b7", "commiter": "Jiaju Zhuang <zhuangjiaju@qq.com>", "date": "2020-03-15 04:06:04", "context": "", "issues": []}, {"line": 51, "commitId": "easyexcel_107", "commitHash": "e63190976af92983c9e3e1de6c065628bc26b3b7", "commiter": "Jiaju Zhuang <zhuangjiaju@qq.com>", "date": "2020-03-15 04:06:04", "context": "}", "issues": []}]}